pyVME/__init__.py
pyVME/client.py
pyVME/fpga.py
pyVME/server.py
pyVME/vme_fpga_py.cpython-311-x86_64-linux-gnu.so
pyVME-1.0.2.dist-info/LICENSE
pyVME-1.0.2.dist-info/METADATA
pyVME-1.0.2.dist-info/WHEEL
pyVME-1.0.2.dist-info/top_level.txt
pyVME-1.0.2.dist-info/RECORD
