Metadata-Version: 2.1
Name: pyVME
Version: 1.0.2
Summary: A small python VME integration, that uses an exposed cpp vme library to interact with a FPGA and can act as a user<->server system
Author-email: Dominic Schüchter <schuechter@hiskp.uni-bonn.de>
Project-URL: Homepage, https://github.com/dschuechter/pyVME
Classifier: Programming Language :: Python :: 3
Classifier: License :: OSI Approved :: GNU General Public License v3 or later (GPLv3+)
Classifier: Operating System :: POSIX :: Linux
Requires-Python: >=3.9
License-File: LICENSE
